{"eYpKcT3gxZA6i1+BrdkrnA==":"001-576x432.jpg","zTz/JhJbP8+jfqIEsKMJiA==":"002-576x432.jpg","+GyjWAZon0+idok6FvTWVg==":"003-576x432.jpg","z7AUhYYEbItPyB/oNh5xkg==":"004-576x432.jpg","OBoHk4kRKlAPfqpPK+5meg==":"005-576x432.jpg","nrkhZhcXYEkeb0QifnoyEw==":"006-576x432.jpg","ooK0ZMKkf5k8J6njLzK+6Q==":"007-576x432.jpg","Z8aWKwHf0X/PfaTvb5SfbA==":"008-576x432.jpg","5ON1WJG4eju8h62WFjCj7g==":"background3.jpg","dSpOmDQ5Qz9s+7IKBTvvEQ==":"background1.jpg","yGzL5ylmU7w6Fyu6Y6RILA==":"interioramp.jpg","Kwrv0BpG2SQPj5KGBRfdvw==":"mbr.jpg","Q7gjiKbSFdsEi6c2+hgpMw==":"mbr-1.jpg","E37o9bdf6XNBaS7KNZhWMg==":"mbr-2.jpg","X17dJmGgNr+ofP4Ik3M1/g==":"mbr-3.jpg","K2CnIu1bOH4COgJb8ZsXJQ==":"mbr-4.jpg","0pxcuJvvo5+t6B+yAH3puA==":"mbr-5.jpg","gox7WbDnF+jpaHN5ssulGg==":"mbr-6.jpg","Q1Ir3yASK9jQ/mX/SA1aMw==":"mbr-7.jpg","vanI2Dcj9PTNGZ4Il9UHjw==":"mbr-8.jpg","mMmp6+G6F3Vrbj3b9v3vfg==":"mbr-9.jpg","2kJ6PazJNfzvs56Le4hoXA==":"mbr-10.jpg","JGxltAfZf1gELeXKIWEuoQ==":"mbr-11.jpg","U88oVrDf+MCAA5ZptK3SlQ==":"mbr-12.jpg","OvdDcMfL5Q9YAcDs7153qw==":"mbr-13.jpg","pJv/SAsa971sJ3mWMHtwUA==":"mbr-14.jpg","p5MdvYSOKHlXXKwsLppPrw==":"mbr-15.jpg","qpZc9HaDXrfDDVBcVgPDhA==":"mbr-16.jpg","TBN5LPquk6Yh7Kcl5waPQQ==":"mbr-17.jpg","3eiF2oXlCE7D9e/j4uy4fA==":"mbr-18.jpg","oAOLKA7DOqbGdBsHdcyXQQ==":"mbr-19.jpg","Z2Be8ej+HtHkIBlvHOJl6Q==":"mbr-20.jpg","6wjmyKZ5XTpj2xaSDO0alg==":"mbr-21.jpg","SDegDg54ogkHWXwy2YoHqQ==":"mbr-22.jpg","TIB60LCVWvn1ZyFBU+qSFQ==":"mbr-23.jpg","435Ysfwgdwtn6a8jmicntg==":"mbr-24.jpg","McuEei27Xc4OfIN+rqqjuw==":"mbr-25.jpg","ZzuKELZMk0C+gFv4CaTVvg==":"mbr-26.jpg","c+EqUq6ZHzOEmvmBhXkY2Q==":"mbr-27.jpg","CA16s6K62RQ7h2GLMUcH/A==":"mbr-28.jpg","mwEIPHZqPuqp8TXsJSjzXw==":"mbr-29.jpg","8ZMne0uhwZW78TYN2RPidw==":"mbr-30.jpg","d2yePEd3znomrIOiXt8jcg==":"mbr-31.jpg","q4ztlZRKXpz+JBqsyiqPnQ==":"mbr-32.jpg","VjxwHm/mNzIHjL9tU/MW4g==":"mbr-33.jpg","NyxshujMuTzFTbqMIR4iqg==":"mbr-34.jpg","FU10z+VwerhL+1nixka4Sg==":"222.jpg","rXdHl3ZBhaapifxTA5oGFg==":"111.jpg","WTb0XJmGEJQzn3A9sEzW1Q==":"333.jpg","1ZPx5axOW8XN/r3uNyerjw==":"222-1.jpg","utkEAa53q2r/N13bNCJuAw==":"222-2.jpg","t3pIf+IIWPYj57IISHcu2g==":"345345345.jpg","+fjK4laHofjVjxrL4H9GYA==":"mbr-35.jpg","4MU+GV+fmRATSYFLzB0p/g==":"111-1.jpg","zt6eU2G6MgBkQOzhMy5GUQ==":"111-2.jpg","2yRvjQT3471ZFHVOJ1X3Iw==":"222-3.jpg","g7ij4wDrijWQCbrgtjHtzQ==":"111-3.jpg","/rQRtraruMwfrvqVlAeArw==":"222-4.jpg","FfHqU22yKtWhqAZY3Z2AkQ==":"simbolo%20rubi-80x46.png","ynPV86y9etz0woRJzRBhFA==":"simbolo%20marcadagua-1216x693.png","XcLdL3O3/Qn+nhtymxcSvw==":"02_logo%20oficial%20negativa-1216x826.png","SwCMAgh7BqFzT1kGu3oHKg==":"1-1800x1202.png","3XaBMh1sBqeqiRHntEszeQ==":"2-790x528.png","a4WB98r//MNY4jn4j93FtA==":"3-790x528.png","k0B+sn7ldqpm46fL2/Gt3A==":"4-790x528.png","Gd/N0Oh9lvAQqZVEJSvkSQ==":"4-1800x1202.png","9VILx1SMZdNNe8wTVmbNLA==":"7-1800x1189.png","AAKRHV0IEvQPew04RBAZHw==":"7-674x445.png","jvaGM/tHDdV+o0kO2x+pfg==":"7-1-674x445.png","9H/E0B0ATaCv/l2Bf6K5tw==":"simbolo%20branco-120x68.png","a0/88WpxJn0HBO67BMgwnw==":"m1-2000x570.jpg","GZ0iXPsmHn+TlKZIWudZkA==":"m2-2000x570.jpg","qwJ6HbCg4qbZxCiMCYh/WQ==":"m3-2000x599.jpg","d8RMLOvfpH6B/QvsjNflVA==":"6-790x476.png","P1jfOrD6cZ6O/9eDV+/kMA==":"5-790x501.png","iJQ50TbluBmU4HEyS9jMqQ==":"1-790x528.png","pXi06l/e1bZwqsNPgMtFpA==":"simbolo%20branco-300x171.png","7tTdYd2QokrnzLd6XxqOCA==":"simbolo%20neon-300x171.png","JTA2nuqREQfSjCGsywrbng==":"6-1800x1085.png","Uzs3klPPDJQo4lalK5rEXg==":"mbr-10.jpg","l0dwRcUkvcI8Ju8ujigqbw==":"logo-1216x802.png","D24KYGr3IQs+KXYhscpOrg==":"logo-1216x866.png","YVGGPkUNf673zMMqlb9TGQ==":"corp-2000x570.jpg","+Eyg7xyQ/g9ksMaQLTkX9Q==":"lite-1920x1068.jpg","68Jfp63CyBMD+XiMlG4pnA==":"5-1800x1141.png","pzmt0E29EEOrRpXHBVx3Cw==":"1-790x439.jpg","GicBFZ/6gQXFjfDZFYhQUw==":"2-790x439.jpg","OaE/bAUg4/kXm5FhGOn3sQ==":"3-790x439.jpg","tWArRkBKydlHGgIaqQ+iXg==":"4-790x439.jpg","lYyGoIwlm8Md8OrrTOxmkw==":"5-790x439.jpg","xA8rHxAdsLMNuotijS7rDw==":"gallery05.jpg","LZlJ83ZALs2qKn2bGv1Y0g==":"6-790x439.jpg","Jjby9eXx+kuQrXqgIJedpQ==":"7-790x439.jpg","c7D2OgneMFIwoW8sHGwheA==":"8-790x439.jpg","U+DhsC6pOgDeraEhPRE9kA==":"9-790x439.jpg","BW/mBMoVxsWNeWWA9p2zjQ==":"07_logo%20tra%C3%87o%20negativa%20branco-1137x743.png","7t72Csd+x+X4g2zoBD4tRg==":"cozinhas-1920x1068.jpg","7THf7uAI81xZLT9et7QiVQ==":"logo_site-1430x985.png","dz094F7efa2ATEXGz9/h2Q==":"logo_site-1430x1015.png","6VdQppx3mwE3m+grTpfsHg==":"logo_site1-1430x1015.png","QtNC9JJEF0bxZSlUb8P5tA==":"img1.jpg","4iVVwF2qyUPWchmEZWZNhg==":"img2.jpg","B39bsb9oxi31suLxxlSOAQ==":"img5.jpg","RPVLjIHrIAe5i1fR6PDEMA==":"img4.jpg","l0AXM1wST9Xk1tAtKrgdWA==":"img3.jpg","l+BHorPGRBhsZIb+JQ9O1A==":"2-1-790x528.png","kb6NVGkkNjCaZhDsccLoMg==":"2-2-790x528.png","IZEyMDx0qFcrP4jEzfOPrQ==":"3-1-790x528.png","lQROEG9yuTtvXcszfIhpUQ==":"04-1.jpg","tnKXsPi/mKLNc2oL/SSSPg==":"background1-1.jpg","o70fDJ5LOza4cNsyrxirKg==":"1-790x534.png","bGlUECcmyuxU8FBiDjZChw==":"1-790x535.png","Tn9UD1zGxv5HyTmer8f/FQ==":"2-790x534.png","YaHGGPffyYvEvq3R3Wo6pQ==":"3-790x534.png","q9BbYgfz11BQX57iIm0+bQ==":"4-790x534.png","x3truJWkGqUdsXgWJtMplA==":"5-790x534.png","2AUrTjpMVILydDgzWGtMSg==":"6-790x534.png","ztqQHaK+NpFz2pHkbZ1e9A==":"7-790x534.png","q2fXEENRcsB/xw/1Scbu3Q==":"8-790x534.png","hfmkCNig152lVmYlUX/0lg==":"9-790x534.png","YZJ+vFg++Iw9ThNQep5lTA==":"29-1.jpg","AGJ5xyWe4P2ifiQxtiLjDA==":"39-1.jpg","qv5KTuJI3qGFBjX92vM9fQ==":"32-1.jpg","8ZF0SLdditFUWvtlA6kdsQ==":"9-790x531.png","5BlJ9H5atLxU+r3wAq5ytw==":"7-790x531.png","C+XxyJvKA2LJg5nfPAR9nw==":"8-790x531.png","yuQ2qAa5SRuoSlivP/ZY1w==":"6-790x531.png","gNrlJXBb4yosJ7K+tG6+Ew==":"5-790x531.png","ir4BozELtIO+nZTLZHcdBw==":"4-790x531.png","kBGET2mqDxDeKAdlxaQ0zw==":"1-790x531.png","v1h099W0z73EXPBPLYcz3Q==":"2-790x531.png","+i3d6vBpgN31hx/Dj9iuzw==":"3-790x531.png","Yhn+OUyUMNE61SwYl2uLFw==":"3-1-790x531.png","cU+j+KPUv9lFGv8VGSoWFQ==":"textura_inspirarte-1920x1493.png","QB33j/CFz2wOd1X1gN113w==":"insp-1080x422.png","cXUTNVmsPfFPrSkoxAvspQ==":"imagem1-1280x640.jpg","dND2RyNtoBCqetgC7WlrTA==":"imagem2-1281x860.jpg","WnpJsJVo6OTHMrs6Cy4omg==":"2-790x534.png","sFjWabacFAiQact0lqT4fA==":"4-790x534.png","1eXxQ2yRtjJxU9SKgSFiMA==":"7-790x534.png","7AMVZkrJk7rOTu8u4DiPoQ==":"5-790x534.png","8qh/faC0uzxTyGYkzhTjbw==":"6-790x534.png","ozbDe/iqRg5TUMZ2P+Pu7g==":"8-790x534.png","0rccHpeDGwepKL/fArb4dQ==":"3-790x534.png","wgYIT6Gkalt9ED6cQ17T7Q==":"1-790x535.png","qwSGtC9HXsCqYZwdMblnMg==":"background3-1.jpg","fad5qrYahoc0te8O6AYskw==":"log-400x272.png","cIo0VICcoqzsNsThjqxXvA==":"background1-3.jpg","tah/qgwfgMhIcHKbk0RH+w==":"background3.jpg","rHBjP83Tmg0gzh/Xk+Wnqg==":"planejados-597x413.jpg","LNt+hlalFBEi1LHEcwoXvA==":"moveis-378x265.jpg","XF+1+8YbcazXJF+ljAfkDg==":"decor-374x262.png","1J2BjTfFRwvaDp7nRpxbig==":"tapet-378x265.jpg","h4vcqXAXCkTDG25HwlYmZQ==":"persiana-378x265.png","85zyYJSFp41lM8wn+WUHww==":"lumina-373x262.png","NLm+vcWiULzbduL3+/WKiw==":"terap-373x262.png","Ze8ViRKhq81IHskuu1nznQ==":"quadros-374x262.png","c0So7lnwHpp9w9eBD/rkBA==":"linha%20infantil-378x264.png","tLDybir+2kewCGNc7KwV8w==":"1-800x569.png","s6Mq9NXiQX69V22Jj+xVLA==":"2-672x478.png","4eT+UuRc9ddq96XrRyQ9OA==":"3-672x478.png","Sq1ZQWX8DJsUozMKKOmUbw==":"4-672x478.png","y3td79KQDVZnL4ryeG43Ow==":"5-672x478.png","RZhEZrcsesKBpFdtvqL4cw==":"1-1-800x569.png","vxDg2DzbDtTAVzAFyYaDhQ==":"2-1-672x478.png","LS8VZoHrvtYwy9ml+lx26g==":"3-1-672x478.png","wrGVOe7wy1LEHGKSybGVbg==":"4-1-672x478.png","k2dqbbecM0PbPpVFojYZSA==":"5-1-672x478.png","KBHds0DWCrn1BHjZzsQGIw==":"1-2-800x569.png","Z/ji8ulcCaitMgGxV3h6rg==":"2-2-672x478.png","hzBe7J5DwY5ByD18H/Ygcw==":"3-2-672x478.png","LaV6eiVk+XANAyA7P8TA/Q==":"4-2-672x478.png","yOY1+TfBiPZZRa2zobSk5A==":"5-2-672x478.png","+ay/sHqhT7nz1LejrtFxTQ==":"1-3-800x569.png","v9x7dQihhgKy9BDgXQ9eyg==":"2-3-672x478.png","eb3KZt2kRt62Pbvx74zgyQ==":"3-3-672x478.png","Qk5/HcyK+WTHCO1cNhBC9Q==":"4-3-672x478.png","KbDmZN6pmGVO2h9gjXxW6g==":"5-3-672x478.png","ddi7RyT+DSwt+zF917Qd1g==":"1-4-800x569.png","YYfkxBAW7djJolubEe8tVg==":"2-4-672x478.png","jJAYHcHNcl1w7dbllrLshg==":"3-4-672x478.png","Hd5FQR08qFVrRqnJwQ9lcw==":"4-4-672x478.png","fm+AxztWzhCYc9PK3JnggA==":"5-4-672x478.png","pUn3ep7SsZ6EJvHGZyQJ5A==":"1-5-800x569.png","WDAkSU1bQdyFHdqEzMOlRg==":"2-5-672x478.png","kaPFouuCorurhmauSyD/tg==":"3-5-672x478.png","ZXZqIiknZOVTOcrocCUV8A==":"4-5-672x478.png","V5fNw+hb7G60liqMkaazxA==":"5-5-672x478.png","PF40ALbRpt7yWeatNB8y2g==":"1-6-800x569.png","o84wmW3tDTLltGIJbkwDhw==":"2-6-672x478.png","nlGn18BREJvv9Fv9wQ2IUw==":"3-6-672x478.png","BEN29i5wJcEAj2893WgSBQ==":"4-6-672x478.png","JFS4CsJ5KEWHs9CQC3aNkg==":"5-6-672x478.png","gNZ4b3F1hROHcyFlS2CNjQ==":"1-7-800x569.png","AmMi61nU3rb8u8QZS4ouMA==":"2-7-672x478.png","qqQqCIP3ptHKk+ZALMlPMA==":"3-7-672x478.png","5A2XoCzY7ynr6qLfpdOerg==":"4-7-672x478.png","ucdryTlObCAYYuqop+Q8ww==":"5-7-672x478.png","lAD1LdHOGT03Zaq0tymMZQ==":"1-8-800x569.png","xTAzFLNuHh86bVC5kxXVeg==":"2-8-672x478.png","h4DPJrVGy283+D4LqUDvRw==":"3-8-672x478.png","YsBKI6/hd2a5R6XXbasfSg==":"4-8-672x478.png","TFajYP6mnyH+jUubFbSPIw==":"5-8-672x478.png","J3iKwlF4zkDqhYjPJ3wNOQ==":"1-9-800x569.png","0Q7My2RAkWrxg64UJ69+kQ==":"2-9-672x478.png","WiVOeuYPNzD7CpOHJsKuvA==":"3-9-672x478.png","pnEnfIzgmdQw/vNxJU19dg==":"4-9-672x478.png","WtTCPaW4vAyWmrvbmRSMnw==":"5-9-672x478.png","eqaixMvGRv5F10b7anCYpw==":"1-10-800x569.png","C76o4pExKRF2ECQFlVAHlw==":"2-10-672x478.png","2AlUd0bTt5zLPwa8Ig4fEg==":"3-10-672x478.png","mryAotQd1RLAPuKIQyGttQ==":"4-10-672x478.png","jQx9eTfJ6nQfXar3yFJHKw==":"5-10-672x478.png","8PkVQFzPTgYuedIQB/bgiQ==":"1-11-800x569.png","DsobtBYFb5d57zoV9DLZ5Q==":"2-11-672x478.png","HZVll1GgRwQw0bm36FVD8w==":"3-11-672x478.png","By4C6uHqleY5/bpBc/en+g==":"4-11-672x478.png","IPyeOCWd2VH3yQoZ07jaiA==":"5-11-672x478.png","EklxFcw5ns9urOV4s3r1PQ==":"office-397x264.jpeg","EOr1Am5g8a8mN+PWGa1E6Q==":"garden-378x264.jpeg","DE6aIlTbwh57hNye1mJYDw==":"papelpared-2-398x268.png","e2UUpjX3FeGHDItQjQnEaA==":"log-2-276x158.png","yU4eN9A2ujlvVPDp7UXqOw==":"inspirarte_atual-1216x681.png","hR01u1dicqiK3F0AlypEpg==":"7-2-674x445.png","BrMcZuzMNfCByAYxr+MNBQ==":"background2.jpg","/cGwv2azvlD8NBxu0ygTlw==":"imagem1-2000x1125.jpg","aV7x5Fk1WnrBGxeuVHVTng==":"imagem2-2000x1125.jpeg","9kF/ctlb+Ex0Po6sBFgdcA==":"inspirarte_logo-533x373.png","VTzACYWbRE91274WZbsXXQ==":"inspirarte_logo-1-533x373.png","viRHdriesjAYSP8NB2kr7g==":"cel-1216x2631.png","OV2NFwHVRjDhLOVU1y9Qyg==":"cel-600x1298.png","SUM5tFsPzeFjwXKXBKvLhA==":"cel-1216x986.png"}